{".class": "MypyFile", "_fullname": "jax._src.api_util", "future_import_flags": [], "is_partial_stub_package": false, "is_stub": false, "names": {".class": "SymbolTable", "Any": {".class": "SymbolTableNode", "cross_ref": "typing.Any", "kind": "Gdef"}, "Dict": {".class": "SymbolTableNode", "cross_ref": "typing.Dict", "kind": "Gdef"}, "Hashable": {".class": "SymbolTableNode", "cross_ref": "jax._src.util.Hashable", "kind": "Gdef"}, "Iterable": {".class": "SymbolTableNode", "cross_ref": "typing.Iterable", "kind": "Gdef"}, "Optional": {".class": "SymbolTableNode", "cross_ref": "typing.Optional", "kind": "Gdef"}, "PyTreeDef": {".class": "SymbolTableNode", "cross_ref": "jax._src.tree_util.PyTreeDef", "kind": "Gdef"}, "Sequence": {".class": "SymbolTableNode", "cross_ref": "typing.Sequence", "kind": "Gdef"}, "Tuple": {".class": "SymbolTableNode", "cross_ref": "typing.Tuple", "kind": "Gdef"}, "Unhashable": {".class": "SymbolTableNode", "cross_ref": "jax._src.util.Unhashable", "kind": "Gdef"}, "Union": {".class": "SymbolTableNode", "cross_ref": "typing.Union", "kind": "Gdef"}, "WrapKwArgs": {".class": "SymbolTableNode", "cross_ref": "jax._src.util.WrapKwArgs", "kind": "Gdef"}, "_HashableWithStrictTypeEquality": {".class": "SymbolTableNode", "kind": "Gdef", "node": {".class": "TypeInfo", "_promote": [], "abstract_attributes": [], "bases": ["builtins.object"], "declared_metaclass": null, "defn": {".class": "ClassDef", "fullname": "jax._src.api_util._HashableWithStrictTypeEquality", "name": "_HashableWithStrictTypeEquality", "type_vars": []}, "deletable_attributes": [], "flags": [], "fullname": "jax._src.api_util._HashableWithStrictTypeEquality", "has_param_spec_type": false, "metaclass_type": null, "metadata": {}, "module_name": "jax._src.api_util", "mro": ["jax._src.api_util._HashableWithStrictTypeEquality", "builtins.object"], "names": {".class": "SymbolTable", "__eq__": {".class": "SymbolTableNode", "kind": "Mdef", "node": {".class": "FuncDef", "abstract_status": 0, "arg_kinds": [0, 0], "arg_names": [null, null], "flags": [], "fullname": "jax._src.api_util._HashableWithStrictTypeEquality.__eq__", "name": "__eq__", "type": null}}, "__hash__": {".class": "SymbolTableNode", "kind": "Mdef", "node": {".class": "FuncDef", "abstract_status": 0, "arg_kinds": [0], "arg_names": ["self"], "flags": [], "fullname": "jax._src.api_util._HashableWithStrictTypeEquality.__hash__", "name": "__hash__", "type": null}}, "__init__": {".class": "SymbolTableNode", "kind": "Mdef", "node": {".class": "FuncDef", "abstract_status": 0, "arg_kinds": [0, 0], "arg_names": ["self", "val"], "flags": [], "fullname": "jax._src.api_util._HashableWithStrictTypeEquality.__init__", "name": "__init__", "type": null}}, "__slots__": {".class": "SymbolTableNode", "kind": "Mdef", "node": {".class": "Var", "flags": ["is_initialized_in_class", "is_inferred", "has_explicit_value", "allow_incompatible_override"], "fullname": "jax._src.api_util._HashableWithStrictTypeEquality.__slots__", "name": "__slots__", "type": {".class": "Instance", "args": ["builtins.str"], "type_ref": "builtins.list"}}}, "val": {".class": "SymbolTableNode", "implicit": true, "kind": "Mdef", "node": {".class": "Var", "flags": ["is_inferred"], "fullname": "jax._src.api_util._HashableWithStrictTypeEquality.val", "name": "val", "type": {".class": "AnyType", "missing_import_name": null, "source_any": null, "type_of_any": 1}}}}, "slots": ["val"], "tuple_type": null, "type_vars": [], "typeddict_type": null}}, "__annotations__": {".class": "SymbolTableNode", "kind": "Gdef", "node": {".class": "Var", "flags": ["is_ready"], "fullname": "jax._src.api_util.__annotations__", "name": "__annotations__", "type": {".class": "Instance", "args": ["builtins.str", {".class": "AnyType", "missing_import_name": null, "source_any": null, "type_of_any": 6}], "type_ref": "builtins.dict"}}}, "__doc__": {".class": "SymbolTableNode", "kind": "Gdef", "node": {".class": "Var", "flags": ["is_ready"], "fullname": "jax._src.api_util.__doc__", "name": "__doc__", "type": "builtins.str"}}, "__file__": {".class": "SymbolTableNode", "kind": "Gdef", "node": {".class": "Var", "flags": ["is_ready"], "fullname": "jax._src.api_util.__file__", "name": "__file__", "type": "builtins.str"}}, "__name__": {".class": "SymbolTableNode", "kind": "Gdef", "node": {".class": "Var", "flags": ["is_ready"], "fullname": "jax._src.api_util.__name__", "name": "__name__", "type": "builtins.str"}}, "__package__": {".class": "SymbolTableNode", "kind": "Gdef", "node": {".class": "Var", "flags": ["is_ready"], "fullname": "jax._src.api_util.__package__", "name": "__package__", "type": "builtins.str"}}, "_argnames_partial": {".class": "SymbolTableNode", "kind": "Gdef", "node": {".class": "Decorator", "func": {".class": "FuncDef", "abstract_status": 0, "arg_kinds": [0, 2, 4], "arg_names": ["fixed_kwargs", "args", "dyn_kwargs"], "flags": ["is_generator", "is_decorated"], "fullname": "jax._src.api_util._argnames_partial", "name": "_argnames_partial", "type": {".class": "CallableType", "arg_kinds": [0, 2, 4], "arg_names": ["fixed_kwargs", "args", "dyn_kwargs"], "arg_types": ["jax._src.util.WrapKwArgs", {".class": "AnyType", "missing_import_name": null, "source_any": null, "type_of_any": 1}, {".class": "AnyType", "missing_import_name": null, "source_any": null, "type_of_any": 1}], "bound_args": [], "def_extras": {"first_arg": null}, "fallback": "builtins.function", "from_concatenate": false, "implicit": false, "is_ellipsis_args": false, "name": "_argnames_partial", "ret_type": {".class": "AnyType", "missing_import_name": null, "source_any": null, "type_of_any": 1}, "type_guard": null, "unpack_kwargs": false, "variables": []}}, "is_overload": false, "var": {".class": "Var", "flags": ["is_ready", "is_inferred"], "fullname": "jax._src.api_util._argnames_partial", "name": "_argnames_partial", "type": {".class": "AnyType", "missing_import_name": null, "source_any": {".class": "AnyType", "missing_import_name": null, "source_any": null, "type_of_any": 1}, "type_of_any": 7}}}}, "_argnums_partial": {".class": "SymbolTableNode", "kind": "Gdef", "node": {".class": "Decorator", "func": {".class": "FuncDef", "abstract_status": 0, "arg_kinds": [0, 0, 2, 4], "arg_names": ["dyn_argnums", "fixed_args", "dyn_args", "kwargs"], "flags": ["is_generator", "is_decorated"], "fullname": "jax._src.api_util._argnums_partial", "name": "_argnums_partial", "type": null}, "is_overload": false, "var": {".class": "Var", "flags": ["is_ready", "is_inferred"], "fullname": "jax._src.api_util._argnums_partial", "name": "_argnums_partial", "type": {".class": "AnyType", "missing_import_name": null, "source_any": {".class": "AnyType", "missing_import_name": null, "source_any": null, "type_of_any": 1}, "type_of_any": 7}}}}, "_dtype": {".class": "SymbolTableNode", "kind": "Gdef", "node": {".class": "FuncDef", "abstract_status": 0, "arg_kinds": [0], "arg_names": ["x"], "flags": [], "fullname": "jax._src.api_util._dtype", "name": "_dtype", "type": null}}, "_ensure_inbounds": {".class": "SymbolTableNode", "kind": "Gdef", "node": {".class": "FuncDef", "abstract_status": 0, "arg_kinds": [0, 0, 0], "arg_names": ["allow_invalid", "num_args", "argnums"], "flags": [], "fullname": "jax._src.api_util._ensure_inbounds", "name": "_ensure_inbounds", "type": {".class": "CallableType", "arg_kinds": [0, 0, 0], "arg_names": ["allow_invalid", "num_args", "argnums"], "arg_types": ["builtins.bool", "builtins.int", {".class": "Instance", "args": ["builtins.int"], "type_ref": "typing.Sequence"}], "bound_args": [], "def_extras": {"first_arg": null}, "fallback": "builtins.function", "from_concatenate": false, "implicit": false, "is_ellipsis_args": false, "name": "_ensure_inbounds", "ret_type": {".class": "Instance", "args": ["builtins.int"], "type_ref": "builtins.tuple"}, "type_guard": null, "unpack_kwargs": false, "variables": []}}}, "_ensure_index": {".class": "SymbolTableNode", "kind": "Gdef", "node": {".class": "FuncDef", "abstract_status": 0, "arg_kinds": [0], "arg_names": ["x"], "flags": [], "fullname": "jax._src.api_util._ensure_index", "name": "_ensure_index", "type": {".class": "CallableType", "arg_kinds": [0], "arg_names": ["x"], "arg_types": [{".class": "AnyType", "missing_import_name": null, "source_any": null, "type_of_any": 2}], "bound_args": [], "def_extras": {"first_arg": null}, "fallback": "builtins.function", "from_concatenate": false, "implicit": false, "is_ellipsis_args": false, "name": "_ensure_index", "ret_type": {".class": "UnionType", "items": ["builtins.int", {".class": "Instance", "args": ["builtins.int"], "type_ref": "builtins.tuple"}]}, "type_guard": null, "unpack_kwargs": false, "variables": []}}}, "_ensure_index_tuple": {".class": "SymbolTableNode", "kind": "Gdef", "node": {".class": "FuncDef", "abstract_status": 0, "arg_kinds": [0], "arg_names": ["x"], "flags": [], "fullname": "jax._src.api_util._ensure_index_tuple", "name": "_ensure_index_tuple", "type": {".class": "CallableType", "arg_kinds": [0], "arg_names": ["x"], "arg_types": [{".class": "AnyType", "missing_import_name": null, "source_any": null, "type_of_any": 2}], "bound_args": [], "def_extras": {"first_arg": null}, "fallback": "builtins.function", "from_concatenate": false, "implicit": false, "is_ellipsis_args": false, "name": "_ensure_index_tuple", "ret_type": {".class": "Instance", "args": ["builtins.int"], "type_ref": "builtins.tuple"}, "type_guard": null, "unpack_kwargs": false, "variables": []}}}, "_ensure_str": {".class": "SymbolTableNode", "kind": "Gdef", "node": {".class": "FuncDef", "abstract_status": 0, "arg_kinds": [0], "arg_names": ["x"], "flags": [], "fullname": "jax._src.api_util._ensure_str", "name": "_ensure_str", "type": {".class": "CallableType", "arg_kinds": [0], "arg_names": ["x"], "arg_types": ["builtins.str"], "bound_args": [], "def_extras": {"first_arg": null}, "fallback": "builtins.function", "from_concatenate": false, "implicit": false, "is_ellipsis_args": false, "name": "_ensure_str", "ret_type": "builtins.str", "type_guard": null, "unpack_kwargs": false, "variables": []}}}, "_ensure_str_tuple": {".class": "SymbolTableNode", "kind": "Gdef", "node": {".class": "FuncDef", "abstract_status": 0, "arg_kinds": [0], "arg_names": ["x"], "flags": [], "fullname": "jax._src.api_util._ensure_str_tuple", "name": "_ensure_str_tuple", "type": {".class": "CallableType", "arg_kinds": [0], "arg_names": ["x"], "arg_types": [{".class": "UnionType", "items": ["builtins.str", {".class": "Instance", "args": ["builtins.str"], "type_ref": "typing.Iterable"}]}], "bound_args": [], "def_extras": {"first_arg": null}, "fallback": "builtins.function", "from_concatenate": false, "implicit": false, "is_ellipsis_args": false, "name": "_ensure_str_tuple", "ret_type": {".class": "Instance", "args": ["builtins.str"], "type_ref": "builtins.tuple"}, "type_guard": null, "unpack_kwargs": false, "variables": []}}}, "_replace_nones": {".class": "SymbolTableNode", "cross_ref": "jax._src.tree_util._replace_nones", "kind": "Gdef"}, "api_hook": {".class": "SymbolTableNode", "kind": "Gdef", "node": {".class": "FuncDef", "abstract_status": 0, "arg_kinds": [0, 0], "arg_names": ["fun", "tag"], "flags": [], "fullname": "jax._src.api_util.api_hook", "name": "api_hook", "type": {".class": "CallableType", "arg_kinds": [0, 0], "arg_names": ["fun", "tag"], "arg_types": [{".class": "AnyType", "missing_import_name": null, "source_any": null, "type_of_any": 1}, "builtins.str"], "bound_args": [], "def_extras": {"first_arg": null}, "fallback": "builtins.function", "from_concatenate": false, "implicit": false, "is_ellipsis_args": false, "name": "api_hook", "ret_type": {".class": "AnyType", "missing_import_name": null, "source_any": null, "type_of_any": 1}, "type_guard": null, "unpack_kwargs": false, "variables": []}}}, "apply_flat_fun": {".class": "SymbolTableNode", "kind": "Gdef", "node": {".class": "FuncDef", "abstract_status": 0, "arg_kinds": [0, 0, 2], "arg_names": ["fun", "io_tree", "py_args"], "flags": [], "fullname": "jax._src.api_util.apply_flat_fun", "name": "apply_flat_fun", "type": null}}, "apply_flat_fun_nokwargs": {".class": "SymbolTableNode", "kind": "Gdef", "node": {".class": "FuncDef", "abstract_status": 0, "arg_kinds": [0, 0, 0], "arg_names": ["fun", "io_tree", "py_args"], "flags": [], "fullname": "jax._src.api_util.apply_flat_fun_nokwargs", "name": "apply_flat_fun_nokwargs", "type": null}}, "argnames_partial_except": {".class": "SymbolTableNode", "kind": "Gdef", "node": {".class": "FuncDef", "abstract_status": 0, "arg_kinds": [0, 0, 0], "arg_names": ["f", "static_argnames", "kwargs"], "flags": [], "fullname": "jax._src.api_util.argnames_partial_except", "name": "argnames_partial_except", "type": {".class": "CallableType", "arg_kinds": [0, 0, 0], "arg_names": ["f", "static_argnames", "kwargs"], "arg_types": ["jax.linear_util.WrappedFun", {".class": "Instance", "args": ["builtins.str"], "type_ref": "builtins.tuple"}, {".class": "Instance", "args": ["builtins.str", {".class": "AnyType", "missing_import_name": null, "source_any": null, "type_of_any": 2}], "type_ref": "builtins.dict"}], "bound_args": [], "def_extras": {"first_arg": null}, "fallback": "builtins.function", "from_concatenate": false, "implicit": false, "is_ellipsis_args": false, "name": "argnames_partial_except", "ret_type": {".class": "AnyType", "missing_import_name": null, "source_any": null, "type_of_any": 1}, "type_guard": null, "unpack_kwargs": false, "variables": []}}}, "argnums_partial": {".class": "SymbolTableNode", "kind": "Gdef", "node": {".class": "FuncDef", "abstract_status": 0, "arg_kinds": [0, 0, 0, 1], "arg_names": ["f", "dyn_argnums", "args", "require_static_args_hashable"], "flags": [], "fullname": "jax._src.api_util.argnums_partial", "name": "argnums_partial", "type": null}}, "argnums_partial_except": {".class": "SymbolTableNode", "kind": "Gdef", "node": {".class": "FuncDef", "abstract_status": 0, "arg_kinds": [0, 0, 0, 3], "arg_names": ["f", "static_argnums", "args", "allow_invalid"], "flags": [], "fullname": "jax._src.api_util.argnums_partial_except", "name": "argnums_partial_except", "type": {".class": "CallableType", "arg_kinds": [0, 0, 0, 3], "arg_names": ["f", "static_argnums", "args", "allow_invalid"], "arg_types": ["jax.linear_util.WrappedFun", {".class": "Instance", "args": ["builtins.int"], "type_ref": "builtins.tuple"}, {".class": "TupleType", "implicit": false, "items": [{".class": "AnyType", "missing_import_name": null, "source_any": null, "type_of_any": 2}], "partial_fallback": {".class": "Instance", "args": [{".class": "AnyType", "missing_import_name": null, "source_any": null, "type_of_any": 6}], "type_ref": "builtins.tuple"}}, "builtins.bool"], "bound_args": [], "def_extras": {"first_arg": null}, "fallback": "builtins.function", "from_concatenate": false, "implicit": false, "is_ellipsis_args": false, "name": "argnums_partial_except", "ret_type": {".class": "AnyType", "missing_import_name": null, "source_any": null, "type_of_any": 1}, "type_guard": null, "unpack_kwargs": false, "variables": []}}}, "core": {".class": "SymbolTableNode", "cross_ref": "jax.core", "kind": "Gdef"}, "donation_vector": {".class": "SymbolTableNode", "kind": "Gdef", "node": {".class": "FuncDef", "abstract_status": 0, "arg_kinds": [0, 0, 0], "arg_names": ["donate_argnums", "args", "kwargs"], "flags": [], "fullname": "jax._src.api_util.donation_vector", "name": "donation_vector", "type": {".class": "CallableType", "arg_kinds": [0, 0, 0], "arg_names": ["donate_argnums", "args", "kwargs"], "arg_types": [{".class": "AnyType", "missing_import_name": null, "source_any": null, "type_of_any": 1}, {".class": "AnyType", "missing_import_name": null, "source_any": null, "type_of_any": 1}, {".class": "AnyType", "missing_import_name": null, "source_any": null, "type_of_any": 1}], "bound_args": [], "def_extras": {"first_arg": null}, "fallback": "builtins.function", "from_concatenate": false, "implicit": false, "is_ellipsis_args": false, "name": "donation_vector", "ret_type": {".class": "Instance", "args": ["builtins.bool"], "type_ref": "builtins.tuple"}, "type_guard": null, "unpack_kwargs": false, "variables": []}}}, "dtypes": {".class": "SymbolTableNode", "cross_ref": "jax._src.dtypes", "kind": "Gdef"}, "flatten_axes": {".class": "SymbolTableNode", "kind": "Gdef", "node": {".class": "FuncDef", "abstract_status": 0, "arg_kinds": [0, 0, 0, 5, 5], "arg_names": ["name", "treedef", "axis_tree", "kws", "tupled_args"], "flags": [], "fullname": "jax._src.api_util.flatten_axes", "name": "flatten_axes", "type": null}}, "flatten_fun": {".class": "SymbolTableNode", "kind": "Gdef", "node": {".class": "Decorator", "func": {".class": "FuncDef", "abstract_status": 0, "arg_kinds": [0, 2], "arg_names": ["in_tree", "args_flat"], "flags": ["is_generator", "is_decorated"], "fullname": "jax._src.api_util.flatten_fun", "name": "flatten_fun", "type": null}, "is_overload": false, "var": {".class": "Var", "flags": ["is_ready", "is_inferred"], "fullname": "jax._src.api_util.flatten_fun", "name": "flatten_fun", "type": {".class": "AnyType", "missing_import_name": null, "source_any": {".class": "AnyType", "missing_import_name": null, "source_any": null, "type_of_any": 1}, "type_of_any": 7}}}}, "flatten_fun_nokwargs": {".class": "SymbolTableNode", "kind": "Gdef", "node": {".class": "Decorator", "func": {".class": "FuncDef", "abstract_status": 0, "arg_kinds": [0, 2], "arg_names": ["in_tree", "args_flat"], "flags": ["is_generator", "is_decorated"], "fullname": "jax._src.api_util.flatten_fun_nokwargs", "name": "flatten_fun_nokwargs", "type": null}, "is_overload": false, "var": {".class": "Var", "flags": ["is_ready", "is_inferred"], "fullname": "jax._src.api_util.flatten_fun_nokwargs", "name": "flatten_fun_nokwargs", "type": {".class": "AnyType", "missing_import_name": null, "source_any": {".class": "AnyType", "missing_import_name": null, "source_any": null, "type_of_any": 1}, "type_of_any": 7}}}}, "flatten_fun_nokwargs2": {".class": "SymbolTableNode", "kind": "Gdef", "node": {".class": "Decorator", "func": {".class": "FuncDef", "abstract_status": 0, "arg_kinds": [0, 2], "arg_names": ["in_tree", "args_flat"], "flags": ["is_generator", "is_decorated"], "fullname": "jax._src.api_util.flatten_fun_nokwargs2", "name": "flatten_fun_nokwargs2", "type": null}, "is_overload": false, "var": {".class": "Var", "flags": ["is_ready", "is_inferred"], "fullname": "jax._src.api_util.flatten_fun_nokwargs2", "name": "flatten_fun_nokwargs2", "type": {".class": "AnyType", "missing_import_name": null, "source_any": {".class": "AnyType", "missing_import_name": null, "source_any": null, "type_of_any": 1}, "type_of_any": 7}}}}, "flattened_fun_in_tree": {".class": "SymbolTableNode", "kind": "Gdef", "node": {".class": "FuncDef", "abstract_status": 0, "arg_kinds": [0], "arg_names": ["fn"], "flags": [], "fullname": "jax._src.api_util.flattened_fun_in_tree", "name": "flattened_fun_in_tree", "type": {".class": "CallableType", "arg_kinds": [0], "arg_names": ["fn"], "arg_types": ["jax.linear_util.WrappedFun"], "bound_args": [], "def_extras": {"first_arg": null}, "fallback": "builtins.function", "from_concatenate": false, "implicit": false, "is_ellipsis_args": false, "name": "flattened_fun_in_tree", "ret_type": {".class": "UnionType", "items": [{".class": "TupleType", "implicit": false, "items": ["jaxlib.xla_extension.pytree.PyTreeDef", "builtins.bool"], "partial_fallback": {".class": "Instance", "args": [{".class": "AnyType", "missing_import_name": null, "source_any": null, "type_of_any": 6}], "type_ref": "builtins.tuple"}}, {".class": "NoneType"}]}, "type_guard": null, "unpack_kwargs": false, "variables": []}}}, "is_hashable": {".class": "SymbolTableNode", "kind": "Gdef", "node": {".class": "FuncDef", "abstract_status": 0, "arg_kinds": [0], "arg_names": ["arg"], "flags": [], "fullname": "jax._src.api_util.is_hashable", "name": "is_hashable", "type": null}}, "lu": {".class": "SymbolTableNode", "cross_ref": "jax.linear_util", "kind": "Gdef"}, "map": {".class": "SymbolTableNode", "kind": "Gdef", "node": {".class": "Var", "flags": ["is_inferred", "has_explicit_value"], "fullname": "jax._src.api_util.map", "name": "map", "type": {".class": "CallableType", "arg_kinds": [0, 2], "arg_names": ["f", "args"], "arg_types": [{".class": "AnyType", "missing_import_name": null, "source_any": null, "type_of_any": 1}, {".class": "AnyType", "missing_import_name": null, "source_any": null, "type_of_any": 1}], "bound_args": [], "def_extras": {"first_arg": null}, "fallback": "builtins.function", "from_concatenate": false, "implicit": true, "is_ellipsis_args": false, "name": null, "ret_type": {".class": "AnyType", "missing_import_name": null, "source_any": null, "type_of_any": 1}, "type_guard": null, "unpack_kwargs": false, "variables": []}}}, "np": {".class": "SymbolTableNode", "cross_ref": "numpy", "kind": "Gdef"}, "operator": {".class": "SymbolTableNode", "cross_ref": "operator", "kind": "Gdef"}, "partial": {".class": "SymbolTableNode", "cross_ref": "functools.partial", "kind": "Gdef"}, "rebase_donate_argnums": {".class": "SymbolTableNode", "kind": "Gdef", "node": {".class": "FuncDef", "abstract_status": 0, "arg_kinds": [0, 0], "arg_names": ["donate_argnums", "static_argnums"], "flags": [], "fullname": "jax._src.api_util.rebase_donate_argnums", "name": "rebase_donate_argnums", "type": {".class": "CallableType", "arg_kinds": [0, 0], "arg_names": ["donate_argnums", "static_argnums"], "arg_types": [{".class": "AnyType", "missing_import_name": null, "source_any": null, "type_of_any": 1}, {".class": "AnyType", "missing_import_name": null, "source_any": null, "type_of_any": 1}], "bound_args": [], "def_extras": {"first_arg": null}, "fallback": "builtins.function", "from_concatenate": false, "implicit": false, "is_ellipsis_args": false, "name": "rebase_donate_argnums", "ret_type": {".class": "Instance", "args": ["builtins.int"], "type_ref": "builtins.tuple"}, "type_guard": null, "unpack_kwargs": false, "variables": []}}}, "safe_map": {".class": "SymbolTableNode", "cross_ref": "jax._src.util.safe_map", "kind": "Gdef"}, "shaped_abstractify": {".class": "SymbolTableNode", "kind": "Gdef", "node": {".class": "FuncDef", "abstract_status": 0, "arg_kinds": [0], "arg_names": ["x"], "flags": [], "fullname": "jax._src.api_util.shaped_abstractify", "name": "shaped_abstractify", "type": null}}, "traceback_util": {".class": "SymbolTableNode", "cross_ref": "jax._src.traceback_util", "kind": "Gdef"}, "tree_flatten": {".class": "SymbolTableNode", "cross_ref": "jax._src.tree_util.tree_flatten", "kind": "Gdef"}, "tree_map": {".class": "SymbolTableNode", "cross_ref": "jax._src.tree_util.tree_map", "kind": "Gdef"}, "tree_structure": {".class": "SymbolTableNode", "cross_ref": "jax._src.tree_util.tree_structure", "kind": "Gdef"}, "tree_unflatten": {".class": "SymbolTableNode", "cross_ref": "jax._src.tree_util.tree_unflatten", "kind": "Gdef"}, "treedef_children": {".class": "SymbolTableNode", "cross_ref": "jax._src.tree_util.treedef_children", "kind": "Gdef"}, "treedef_is_leaf": {".class": "SymbolTableNode", "cross_ref": "jax._src.tree_util.treedef_is_leaf", "kind": "Gdef"}}, "path": "/home/paperspace/.pyenv/versions/3.10.4/lib/python3.10/site-packages/jax/_src/api_util.py"}