{".class": "MypyFile", "_fullname": "jax.numpy", "future_import_flags": [], "is_partial_stub_package": false, "is_stub": false, "names": {".class": "SymbolTable", "ComplexWarning": {".class": "SymbolTableNode", "cross_ref": "jax._src.numpy.lax_numpy.ComplexWarning", "kind": "Gdef"}, "DeviceArray": {".class": "SymbolTableNode", "cross_ref": "jax._src.device_array.DeviceArray", "kind": "Gdef"}, "NINF": {".class": "SymbolTableNode", "cross_ref": "jax._src.numpy.lax_numpy.NINF", "kind": "Gdef"}, "NZERO": {".class": "SymbolTableNode", "cross_ref": "jax._src.numpy.lax_numpy.NZERO", "kind": "Gdef"}, "PZERO": {".class": "SymbolTableNode", "cross_ref": "jax._src.numpy.lax_numpy.PZERO", "kind": "Gdef"}, "_NOT_IMPLEMENTED": {".class": "SymbolTableNode", "cross_ref": "jax._src.numpy.lax_numpy._NOT_IMPLEMENTED", "kind": "Gdef"}, "__annotations__": {".class": "SymbolTableNode", "kind": "Gdef", "node": {".class": "Var", "flags": ["is_ready"], "fullname": "jax.numpy.__annotations__", "name": "__annotations__", "type": {".class": "Instance", "args": ["builtins.str", {".class": "AnyType", "missing_import_name": null, "source_any": null, "type_of_any": 6}], "type_ref": "builtins.dict"}}}, "__doc__": {".class": "SymbolTableNode", "kind": "Gdef", "node": {".class": "Var", "flags": ["is_ready"], "fullname": "jax.numpy.__doc__", "name": "__doc__", "type": "builtins.str"}}, "__file__": {".class": "SymbolTableNode", "kind": "Gdef", "node": {".class": "Var", "flags": ["is_ready"], "fullname": "jax.numpy.__file__", "name": "__file__", "type": "builtins.str"}}, "__name__": {".class": "SymbolTableNode", "kind": "Gdef", "node": {".class": "Var", "flags": ["is_ready"], "fullname": "jax.numpy.__name__", "name": "__name__", "type": "builtins.str"}}, "__package__": {".class": "SymbolTableNode", "kind": "Gdef", "node": {".class": "Var", "flags": ["is_ready"], "fullname": "jax.numpy.__package__", "name": "__package__", "type": "builtins.str"}}, "__path__": {".class": "SymbolTableNode", "kind": "Gdef", "node": {".class": "Var", "flags": ["is_ready"], "fullname": "jax.numpy.__path__", "name": "__path__", "type": {".class": "Instance", "args": ["builtins.str"], "type_ref": "builtins.list"}}}, "_init": {".class": "SymbolTableNode", "kind": "Gdef", "node": {".class": "FuncDef", "abstract_status": 0, "arg_kinds": [], "arg_names": [], "flags": [], "fullname": "jax.numpy._init", "name": "_init", "type": null}}, "abs": {".class": "SymbolTableNode", "cross_ref": "jax._src.numpy.ufuncs.abs", "kind": "Gdef"}, "absolute": {".class": "SymbolTableNode", "cross_ref": "jax._src.numpy.ufuncs.absolute", "kind": "Gdef"}, "add": {".class": "SymbolTableNode", "cross_ref": "jax._src.numpy.ufuncs.add", "kind": "Gdef"}, "all": {".class": "SymbolTableNode", "cross_ref": "jax._src.numpy.reductions.all", "kind": "Gdef"}, "allclose": {".class": "SymbolTableNode", "cross_ref": "jax._src.numpy.lax_numpy.allclose", "kind": "Gdef"}, "alltrue": {".class": "SymbolTableNode", "cross_ref": "jax._src.numpy.reductions.alltrue", "kind": "Gdef"}, "amax": {".class": "SymbolTableNode", "cross_ref": "jax._src.numpy.reductions.amax", "kind": "Gdef"}, "amin": {".class": "SymbolTableNode", "cross_ref": "jax._src.numpy.reductions.amin", "kind": "Gdef"}, "angle": {".class": "SymbolTableNode", "cross_ref": "jax._src.numpy.lax_numpy.angle", "kind": "Gdef"}, "any": {".class": "SymbolTableNode", "cross_ref": "jax._src.numpy.reductions.any", "kind": "Gdef"}, "append": {".class": "SymbolTableNode", "cross_ref": "jax._src.numpy.lax_numpy.append", "kind": "Gdef"}, "apply_along_axis": {".class": "SymbolTableNode", "cross_ref": "jax._src.numpy.lax_numpy.apply_along_axis", "kind": "Gdef"}, "apply_over_axes": {".class": "SymbolTableNode", "cross_ref": "jax._src.numpy.lax_numpy.apply_over_axes", "kind": "Gdef"}, "arange": {".class": "SymbolTableNode", "cross_ref": "jax._src.numpy.lax_numpy.arange", "kind": "Gdef"}, "arccos": {".class": "SymbolTableNode", "cross_ref": "jax._src.numpy.ufuncs.arccos", "kind": "Gdef"}, "arccosh": {".class": "SymbolTableNode", "cross_ref": "jax._src.numpy.ufuncs.arccosh", "kind": "Gdef"}, "arcsin": {".class": "SymbolTableNode", "cross_ref": "jax._src.numpy.ufuncs.arcsin", "kind": "Gdef"}, "arcsinh": {".class": "SymbolTableNode", "cross_ref": "jax._src.numpy.ufuncs.arcsinh", "kind": "Gdef"}, "arctan": {".class": "SymbolTableNode", "cross_ref": "jax._src.numpy.ufuncs.arctan", "kind": "Gdef"}, "arctan2": {".class": "SymbolTableNode", "cross_ref": "jax._src.numpy.ufuncs.arctan2", "kind": "Gdef"}, "arctanh": {".class": "SymbolTableNode", "cross_ref": "jax._src.numpy.ufuncs.arctanh", "kind": "Gdef"}, "argmax": {".class": "SymbolTableNode", "cross_ref": "jax._src.numpy.lax_numpy.argmax", "kind": "Gdef"}, "argmin": {".class": "SymbolTableNode", "cross_ref": "jax._src.numpy.lax_numpy.argmin", "kind": "Gdef"}, "argsort": {".class": "SymbolTableNode", "cross_ref": "jax._src.numpy.lax_numpy.argsort", "kind": "Gdef"}, "argwhere": {".class": "SymbolTableNode", "cross_ref": "jax._src.numpy.lax_numpy.argwhere", "kind": "Gdef"}, "around": {".class": "SymbolTableNode", "cross_ref": "jax._src.numpy.lax_numpy.around", "kind": "Gdef"}, "array": {".class": "SymbolTableNode", "cross_ref": "jax._src.numpy.lax_numpy.array", "kind": "Gdef"}, "array_equal": {".class": "SymbolTableNode", "cross_ref": "jax._src.numpy.lax_numpy.array_equal", "kind": "Gdef"}, "array_equiv": {".class": "SymbolTableNode", "cross_ref": "jax._src.numpy.lax_numpy.array_equiv", "kind": "Gdef"}, "array_repr": {".class": "SymbolTableNode", "cross_ref": "jax._src.numpy.lax_numpy.array_repr", "kind": "Gdef"}, "array_split": {".class": "SymbolTableNode", "cross_ref": "jax._src.numpy.lax_numpy.array_split", "kind": "Gdef"}, "array_str": {".class": "SymbolTableNode", "cross_ref": "jax._src.numpy.lax_numpy.array_str", "kind": "Gdef"}, "asarray": {".class": "SymbolTableNode", "cross_ref": "jax._src.numpy.lax_numpy.asarray", "kind": "Gdef"}, "atleast_1d": {".class": "SymbolTableNode", "cross_ref": "jax._src.numpy.lax_numpy.atleast_1d", "kind": "Gdef"}, "atleast_2d": {".class": "SymbolTableNode", "cross_ref": "jax._src.numpy.lax_numpy.atleast_2d", "kind": "Gdef"}, "atleast_3d": {".class": "SymbolTableNode", "cross_ref": "jax._src.numpy.lax_numpy.atleast_3d", "kind": "Gdef"}, "average": {".class": "SymbolTableNode", "cross_ref": "jax._src.numpy.reductions.average", "kind": "Gdef"}, "bartlett": {".class": "SymbolTableNode", "cross_ref": "jax._src.numpy.lax_numpy.bartlett", "kind": "Gdef"}, "bfloat16": {".class": "SymbolTableNode", "cross_ref": "jax._src.numpy.lax_numpy.bfloat16", "kind": "Gdef"}, "bincount": {".class": "SymbolTableNode", "cross_ref": "jax._src.numpy.lax_numpy.bincount", "kind": "Gdef"}, "bitwise_and": {".class": "SymbolTableNode", "cross_ref": "jax._src.numpy.ufuncs.bitwise_and", "kind": "Gdef"}, "bitwise_not": {".class": "SymbolTableNode", "cross_ref": "jax._src.numpy.ufuncs.bitwise_not", "kind": "Gdef"}, "bitwise_or": {".class": "SymbolTableNode", "cross_ref": "jax._src.numpy.ufuncs.bitwise_or", "kind": "Gdef"}, "bitwise_xor": {".class": "SymbolTableNode", "cross_ref": "jax._src.numpy.ufuncs.bitwise_xor", "kind": "Gdef"}, "blackman": {".class": "SymbolTableNode", "cross_ref": "jax._src.numpy.lax_numpy.blackman", "kind": "Gdef"}, "block": {".class": "SymbolTableNode", "cross_ref": "jax._src.numpy.lax_numpy.block", "kind": "Gdef"}, "bool_": {".class": "SymbolTableNode", "cross_ref": "jax._src.numpy.lax_numpy.bool_", "kind": "Gdef"}, "broadcast_arrays": {".class": "SymbolTableNode", "cross_ref": "jax._src.numpy.lax_numpy.broadcast_arrays", "kind": "Gdef"}, "broadcast_shapes": {".class": "SymbolTableNode", "cross_ref": "jax._src.numpy.lax_numpy.broadcast_shapes", "kind": "Gdef"}, "broadcast_to": {".class": "SymbolTableNode", "cross_ref": "jax._src.numpy.lax_numpy.broadcast_to", "kind": "Gdef"}, "c_": {".class": "SymbolTableNode", "cross_ref": "jax._src.numpy.index_tricks.c_", "kind": "Gdef"}, "can_cast": {".class": "SymbolTableNode", "cross_ref": "jax._src.numpy.lax_numpy.can_cast", "kind": "Gdef"}, "cbrt": {".class": "SymbolTableNode", "cross_ref": "jax._src.numpy.ufuncs.cbrt", "kind": "Gdef"}, "cdouble": {".class": "SymbolTableNode", "cross_ref": "jax._src.numpy.lax_numpy.cdouble", "kind": "Gdef"}, "ceil": {".class": "SymbolTableNode", "cross_ref": "jax._src.numpy.ufuncs.ceil", "kind": "Gdef"}, "character": {".class": "SymbolTableNode", "cross_ref": "jax._src.numpy.lax_numpy.character", "kind": "Gdef"}, "choose": {".class": "SymbolTableNode", "cross_ref": "jax._src.numpy.lax_numpy.choose", "kind": "Gdef"}, "clip": {".class": "SymbolTableNode", "cross_ref": "jax._src.numpy.lax_numpy.clip", "kind": "Gdef"}, "column_stack": {".class": "SymbolTableNode", "cross_ref": "jax._src.numpy.lax_numpy.column_stack", "kind": "Gdef"}, "complex128": {".class": "SymbolTableNode", "cross_ref": "jax._src.numpy.lax_numpy.complex128", "kind": "Gdef"}, "complex64": {".class": "SymbolTableNode", "cross_ref": "jax._src.numpy.lax_numpy.complex64", "kind": "Gdef"}, "complex_": {".class": "SymbolTableNode", "cross_ref": "jax._src.numpy.lax_numpy.complex_", "kind": "Gdef"}, "complexfloating": {".class": "SymbolTableNode", "cross_ref": "jax._src.numpy.lax_numpy.complexfloating", "kind": "Gdef"}, "compress": {".class": "SymbolTableNode", "cross_ref": "jax._src.numpy.lax_numpy.compress", "kind": "Gdef"}, "concatenate": {".class": "SymbolTableNode", "cross_ref": "jax._src.numpy.lax_numpy.concatenate", "kind": "Gdef"}, "conj": {".class": "SymbolTableNode", "cross_ref": "jax._src.numpy.ufuncs.conj", "kind": "Gdef"}, "conjugate": {".class": "SymbolTableNode", "cross_ref": "jax._src.numpy.ufuncs.conjugate", "kind": "Gdef"}, "convolve": {".class": "SymbolTableNode", "cross_ref": "jax._src.numpy.lax_numpy.convolve", "kind": "Gdef"}, "copy": {".class": "SymbolTableNode", "cross_ref": "jax._src.numpy.lax_numpy.copy", "kind": "Gdef"}, "copysign": {".class": "SymbolTableNode", "cross_ref": "jax._src.numpy.ufuncs.copysign", "kind": "Gdef"}, "corrcoef": {".class": "SymbolTableNode", "cross_ref": "jax._src.numpy.lax_numpy.corrcoef", "kind": "Gdef"}, "correlate": {".class": "SymbolTableNode", "cross_ref": "jax._src.numpy.lax_numpy.correlate", "kind": "Gdef"}, "cos": {".class": "SymbolTableNode", "cross_ref": "jax._src.numpy.ufuncs.cos", "kind": "Gdef"}, "cosh": {".class": "SymbolTableNode", "cross_ref": "jax._src.numpy.ufuncs.cosh", "kind": "Gdef"}, "count_nonzero": {".class": "SymbolTableNode", "cross_ref": "jax._src.numpy.reductions.count_nonzero", "kind": "Gdef"}, "cov": {".class": "SymbolTableNode", "cross_ref": "jax._src.numpy.lax_numpy.cov", "kind": "Gdef"}, "cross": {".class": "SymbolTableNode", "cross_ref": "jax._src.numpy.lax_numpy.cross", "kind": "Gdef"}, "csingle": {".class": "SymbolTableNode", "cross_ref": "jax._src.numpy.lax_numpy.csingle", "kind": "Gdef"}, "cumprod": {".class": "SymbolTableNode", "cross_ref": "jax._src.numpy.reductions.cumprod", "kind": "Gdef"}, "cumproduct": {".class": "SymbolTableNode", "cross_ref": "jax._src.numpy.reductions.cumproduct", "kind": "Gdef"}, "cumsum": {".class": "SymbolTableNode", "cross_ref": "jax._src.numpy.reductions.cumsum", "kind": "Gdef"}, "deg2rad": {".class": "SymbolTableNode", "cross_ref": "jax._src.numpy.ufuncs.deg2rad", "kind": "Gdef"}, "degrees": {".class": "SymbolTableNode", "cross_ref": "jax._src.numpy.ufuncs.degrees", "kind": "Gdef"}, "delete": {".class": "SymbolTableNode", "cross_ref": "jax._src.numpy.lax_numpy.delete", "kind": "Gdef"}, "diag": {".class": "SymbolTableNode", "cross_ref": "jax._src.numpy.lax_numpy.diag", "kind": "Gdef"}, "diag_indices": {".class": "SymbolTableNode", "cross_ref": "jax._src.numpy.lax_numpy.diag_indices", "kind": "Gdef"}, "diag_indices_from": {".class": "SymbolTableNode", "cross_ref": "jax._src.numpy.lax_numpy.diag_indices_from", "kind": "Gdef"}, "diagflat": {".class": "SymbolTableNode", "cross_ref": "jax._src.numpy.lax_numpy.diagflat", "kind": "Gdef"}, "diagonal": {".class": "SymbolTableNode", "cross_ref": "jax._src.numpy.lax_numpy.diagonal", "kind": "Gdef"}, "diff": {".class": "SymbolTableNode", "cross_ref": "jax._src.numpy.lax_numpy.diff", "kind": "Gdef"}, "digitize": {".class": "SymbolTableNode", "cross_ref": "jax._src.numpy.lax_numpy.digitize", "kind": "Gdef"}, "divide": {".class": "SymbolTableNode", "cross_ref": "jax._src.numpy.ufuncs.divide", "kind": "Gdef"}, "divmod": {".class": "SymbolTableNode", "cross_ref": "jax._src.numpy.ufuncs.divmod", "kind": "Gdef"}, "dot": {".class": "SymbolTableNode", "cross_ref": "jax._src.numpy.lax_numpy.dot", "kind": "Gdef"}, "double": {".class": "SymbolTableNode", "cross_ref": "jax._src.numpy.lax_numpy.double", "kind": "Gdef"}, "dsplit": {".class": "SymbolTableNode", "cross_ref": "jax._src.numpy.lax_numpy.dsplit", "kind": "Gdef"}, "dstack": {".class": "SymbolTableNode", "cross_ref": "jax._src.numpy.lax_numpy.dstack", "kind": "Gdef"}, "dtype": {".class": "SymbolTableNode", "cross_ref": "jax._src.numpy.lax_numpy.dtype", "kind": "Gdef"}, "e": {".class": "SymbolTableNode", "cross_ref": "jax._src.numpy.lax_numpy.e", "kind": "Gdef"}, "ediff1d": {".class": "SymbolTableNode", "cross_ref": "jax._src.numpy.lax_numpy.ediff1d", "kind": "Gdef"}, "einsum": {".class": "SymbolTableNode", "cross_ref": "jax._src.numpy.lax_numpy.einsum", "kind": "Gdef"}, "einsum_path": {".class": "SymbolTableNode", "cross_ref": "jax._src.numpy.lax_numpy.einsum_path", "kind": "Gdef"}, "empty": {".class": "SymbolTableNode", "cross_ref": "jax._src.numpy.lax_numpy.empty", "kind": "Gdef"}, "empty_like": {".class": "SymbolTableNode", "cross_ref": "jax._src.numpy.lax_numpy.empty_like", "kind": "Gdef"}, "equal": {".class": "SymbolTableNode", "cross_ref": "jax._src.numpy.ufuncs.equal", "kind": "Gdef"}, "euler_gamma": {".class": "SymbolTableNode", "cross_ref": "jax._src.numpy.lax_numpy.euler_gamma", "kind": "Gdef"}, "exp": {".class": "SymbolTableNode", "cross_ref": "jax._src.numpy.ufuncs.exp", "kind": "Gdef"}, "exp2": {".class": "SymbolTableNode", "cross_ref": "jax._src.numpy.ufuncs.exp2", "kind": "Gdef"}, "expand_dims": {".class": "SymbolTableNode", "cross_ref": "jax._src.numpy.lax_numpy.expand_dims", "kind": "Gdef"}, "expm1": {".class": "SymbolTableNode", "cross_ref": "jax._src.numpy.ufuncs.expm1", "kind": "Gdef"}, "extract": {".class": "SymbolTableNode", "cross_ref": "jax._src.numpy.lax_numpy.extract", "kind": "Gdef"}, "eye": {".class": "SymbolTableNode", "cross_ref": "jax._src.numpy.lax_numpy.eye", "kind": "Gdef"}, "fabs": {".class": "SymbolTableNode", "cross_ref": "jax._src.numpy.ufuncs.fabs", "kind": "Gdef"}, "fft": {".class": "SymbolTableNode", "cross_ref": "jax.numpy.fft", "kind": "Gdef"}, "finfo": {".class": "SymbolTableNode", "cross_ref": "jax._src.numpy.lax_numpy.finfo", "kind": "Gdef"}, "fix": {".class": "SymbolTableNode", "cross_ref": "jax._src.numpy.lax_numpy.fix", "kind": "Gdef"}, "flatnonzero": {".class": "SymbolTableNode", "cross_ref": "jax._src.numpy.lax_numpy.flatnonzero", "kind": "Gdef"}, "flexible": {".class": "SymbolTableNode", "cross_ref": "jax._src.numpy.lax_numpy.flexible", "kind": "Gdef"}, "flip": {".class": "SymbolTableNode", "cross_ref": "jax._src.numpy.lax_numpy.flip", "kind": "Gdef"}, "fliplr": {".class": "SymbolTableNode", "cross_ref": "jax._src.numpy.lax_numpy.fliplr", "kind": "Gdef"}, "flipud": {".class": "SymbolTableNode", "cross_ref": "jax._src.numpy.lax_numpy.flipud", "kind": "Gdef"}, "float16": {".class": "SymbolTableNode", "cross_ref": "jax._src.numpy.lax_numpy.float16", "kind": "Gdef"}, "float32": {".class": "SymbolTableNode", "cross_ref": "jax._src.numpy.lax_numpy.float32", "kind": "Gdef"}, "float64": {".class": "SymbolTableNode", "cross_ref": "jax._src.numpy.lax_numpy.float64", "kind": "Gdef"}, "float_": {".class": "SymbolTableNode", "cross_ref": "jax._src.numpy.lax_numpy.float_", "kind": "Gdef"}, "float_power": {".class": "SymbolTableNode", "cross_ref": "jax._src.numpy.ufuncs.float_power", "kind": "Gdef"}, "floating": {".class": "SymbolTableNode", "cross_ref": "jax._src.numpy.lax_numpy.floating", "kind": "Gdef"}, "floor": {".class": "SymbolTableNode", "cross_ref": "jax._src.numpy.ufuncs.floor", "kind": "Gdef"}, "floor_divide": {".class": "SymbolTableNode", "cross_ref": "jax._src.numpy.ufuncs.floor_divide", "kind": "Gdef"}, "fmax": {".class": "SymbolTableNode", "cross_ref": "jax._src.numpy.lax_numpy.fmax", "kind": "Gdef"}, "fmin": {".class": "SymbolTableNode", "cross_ref": "jax._src.numpy.lax_numpy.fmin", "kind": "Gdef"}, "fmod": {".class": "SymbolTableNode", "cross_ref": "jax._src.numpy.ufuncs.fmod", "kind": "Gdef"}, "frexp": {".class": "SymbolTableNode", "cross_ref": "jax._src.numpy.ufuncs.frexp", "kind": "Gdef"}, "frombuffer": {".class": "SymbolTableNode", "cross_ref": "jax._src.numpy.lax_numpy.frombuffer", "kind": "Gdef"}, "fromfile": {".class": "SymbolTableNode", "cross_ref": "jax._src.numpy.lax_numpy.fromfile", "kind": "Gdef"}, "fromfunction": {".class": "SymbolTableNode", "cross_ref": "jax._src.numpy.lax_numpy.fromfunction", "kind": "Gdef"}, "fromiter": {".class": "SymbolTableNode", "cross_ref": "jax._src.numpy.lax_numpy.fromiter", "kind": "Gdef"}, "fromstring": {".class": "SymbolTableNode", "cross_ref": "jax._src.numpy.lax_numpy.fromstring", "kind": "Gdef"}, "full": {".class": "SymbolTableNode", "cross_ref": "jax._src.numpy.lax_numpy.full", "kind": "Gdef"}, "full_like": {".class": "SymbolTableNode", "cross_ref": "jax._src.numpy.lax_numpy.full_like", "kind": "Gdef"}, "gcd": {".class": "SymbolTableNode", "cross_ref": "jax._src.numpy.lax_numpy.gcd", "kind": "Gdef"}, "generic": {".class": "SymbolTableNode", "cross_ref": "jax._src.numpy.lax_numpy.generic", "kind": "Gdef"}, "geomspace": {".class": "SymbolTableNode", "cross_ref": "jax._src.numpy.lax_numpy.geomspace", "kind": "Gdef"}, "get_printoptions": {".class": "SymbolTableNode", "cross_ref": "jax._src.numpy.lax_numpy.get_printoptions", "kind": "Gdef"}, "gradient": {".class": "SymbolTableNode", "cross_ref": "jax._src.numpy.lax_numpy.gradient", "kind": "Gdef"}, "greater": {".class": "SymbolTableNode", "cross_ref": "jax._src.numpy.ufuncs.greater", "kind": "Gdef"}, "greater_equal": {".class": "SymbolTableNode", "cross_ref": "jax._src.numpy.ufuncs.greater_equal", "kind": "Gdef"}, "hamming": {".class": "SymbolTableNode", "cross_ref": "jax._src.numpy.lax_numpy.hamming", "kind": "Gdef"}, "hanning": {".class": "SymbolTableNode", "cross_ref": "jax._src.numpy.lax_numpy.hanning", "kind": "Gdef"}, "heaviside": {".class": "SymbolTableNode", "cross_ref": "jax._src.numpy.ufuncs.heaviside", "kind": "Gdef"}, "histogram": {".class": "SymbolTableNode", "cross_ref": "jax._src.numpy.lax_numpy.histogram", "kind": "Gdef"}, "histogram2d": {".class": "SymbolTableNode", "cross_ref": "jax._src.numpy.lax_numpy.histogram2d", "kind": "Gdef"}, "histogram_bin_edges": {".class": "SymbolTableNode", "cross_ref": "jax._src.numpy.lax_numpy.histogram_bin_edges", "kind": "Gdef"}, "histogramdd": {".class": "SymbolTableNode", "cross_ref": "jax._src.numpy.lax_numpy.histogramdd", "kind": "Gdef"}, "hsplit": {".class": "SymbolTableNode", "cross_ref": "jax._src.numpy.lax_numpy.hsplit", "kind": "Gdef"}, "hstack": {".class": "SymbolTableNode", "cross_ref": "jax._src.numpy.lax_numpy.hstack", "kind": "Gdef"}, "hypot": {".class": "SymbolTableNode", "cross_ref": "jax._src.numpy.ufuncs.hypot", "kind": "Gdef"}, "i0": {".class": "SymbolTableNode", "cross_ref": "jax._src.numpy.lax_numpy.i0", "kind": "Gdef"}, "identity": {".class": "SymbolTableNode", "cross_ref": "jax._src.numpy.lax_numpy.identity", "kind": "Gdef"}, "iinfo": {".class": "SymbolTableNode", "cross_ref": "jax._src.numpy.lax_numpy.iinfo", "kind": "Gdef"}, "imag": {".class": "SymbolTableNode", "cross_ref": "jax._src.numpy.ufuncs.imag", "kind": "Gdef"}, "in1d": {".class": "SymbolTableNode", "cross_ref": "jax._src.numpy.setops.in1d", "kind": "Gdef"}, "index_exp": {".class": "SymbolTableNode", "cross_ref": "jax._src.numpy.index_tricks.index_exp", "kind": "Gdef"}, "indices": {".class": "SymbolTableNode", "cross_ref": "jax._src.numpy.lax_numpy.indices", "kind": "Gdef"}, "inexact": {".class": "SymbolTableNode", "cross_ref": "jax._src.numpy.lax_numpy.inexact", "kind": "Gdef"}, "inf": {".class": "SymbolTableNode", "cross_ref": "jax._src.numpy.lax_numpy.inf", "kind": "Gdef"}, "inner": {".class": "SymbolTableNode", "cross_ref": "jax._src.numpy.lax_numpy.inner", "kind": "Gdef"}, "insert": {".class": "SymbolTableNode", "cross_ref": "jax._src.numpy.lax_numpy.insert", "kind": "Gdef"}, "int16": {".class": "SymbolTableNode", "cross_ref": "jax._src.numpy.lax_numpy.int16", "kind": "Gdef"}, "int32": {".class": "SymbolTableNode", "cross_ref": "jax._src.numpy.lax_numpy.int32", "kind": "Gdef"}, "int64": {".class": "SymbolTableNode", "cross_ref": "jax._src.numpy.lax_numpy.int64", "kind": "Gdef"}, "int8": {".class": "SymbolTableNode", "cross_ref": "jax._src.numpy.lax_numpy.int8", "kind": "Gdef"}, "int_": {".class": "SymbolTableNode", "cross_ref": "jax._src.numpy.lax_numpy.int_", "kind": "Gdef"}, "integer": {".class": "SymbolTableNode", "cross_ref": "jax._src.numpy.lax_numpy.integer", "kind": "Gdef"}, "interp": {".class": "SymbolTableNode", "cross_ref": "jax._src.numpy.lax_numpy.interp", "kind": "Gdef"}, "intersect1d": {".class": "SymbolTableNode", "cross_ref": "jax._src.numpy.setops.intersect1d", "kind": "Gdef"}, "invert": {".class": "SymbolTableNode", "cross_ref": "jax._src.numpy.ufuncs.invert", "kind": "Gdef"}, "isclose": {".class": "SymbolTableNode", "cross_ref": "jax._src.numpy.lax_numpy.isclose", "kind": "Gdef"}, "iscomplex": {".class": "SymbolTableNode", "cross_ref": "jax._src.numpy.lax_numpy.iscomplex", "kind": "Gdef"}, "iscomplexobj": {".class": "SymbolTableNode", "cross_ref": "jax._src.numpy.lax_numpy.iscomplexobj", "kind": "Gdef"}, "isfinite": {".class": "SymbolTableNode", "cross_ref": "jax._src.numpy.ufuncs.isfinite", "kind": "Gdef"}, "isin": {".class": "SymbolTableNode", "cross_ref": "jax._src.numpy.setops.isin", "kind": "Gdef"}, "isinf": {".class": "SymbolTableNode", "cross_ref": "jax._src.numpy.ufuncs.isinf", "kind": "Gdef"}, "isnan": {".class": "SymbolTableNode", "cross_ref": "jax._src.numpy.ufuncs.isnan", "kind": "Gdef"}, "isneginf": {".class": "SymbolTableNode", "cross_ref": "jax._src.numpy.ufuncs.isneginf", "kind": "Gdef"}, "isposinf": {".class": "SymbolTableNode", "cross_ref": "jax._src.numpy.ufuncs.isposinf", "kind": "Gdef"}, "isreal": {".class": "SymbolTableNode", "cross_ref": "jax._src.numpy.lax_numpy.isreal", "kind": "Gdef"}, "isrealobj": {".class": "SymbolTableNode", "cross_ref": "jax._src.numpy.lax_numpy.isrealobj", "kind": "Gdef"}, "isscalar": {".class": "SymbolTableNode", "cross_ref": "jax._src.numpy.lax_numpy.isscalar", "kind": "Gdef"}, "issubdtype": {".class": "SymbolTableNode", "cross_ref": "jax._src.numpy.lax_numpy.issubdtype", "kind": "Gdef"}, "issubsctype": {".class": "SymbolTableNode", "cross_ref": "jax._src.numpy.lax_numpy.issubsctype", "kind": "Gdef"}, "iterable": {".class": "SymbolTableNode", "cross_ref": "jax._src.numpy.lax_numpy.iterable", "kind": "Gdef"}, "ix_": {".class": "SymbolTableNode", "cross_ref": "jax._src.numpy.lax_numpy.ix_", "kind": "Gdef"}, "kaiser": {".class": "SymbolTableNode", "cross_ref": "jax._src.numpy.lax_numpy.kaiser", "kind": "Gdef"}, "kron": {".class": "SymbolTableNode", "cross_ref": "jax._src.numpy.lax_numpy.kron", "kind": "Gdef"}, "lcm": {".class": "SymbolTableNode", "cross_ref": "jax._src.numpy.lax_numpy.lcm", "kind": "Gdef"}, "ldexp": {".class": "SymbolTableNode", "cross_ref": "jax._src.numpy.ufuncs.ldexp", "kind": "Gdef"}, "left_shift": {".class": "SymbolTableNode", "cross_ref": "jax._src.numpy.ufuncs.left_shift", "kind": "Gdef"}, "less": {".class": "SymbolTableNode", "cross_ref": "jax._src.numpy.ufuncs.less", "kind": "Gdef"}, "less_equal": {".class": "SymbolTableNode", "cross_ref": "jax._src.numpy.ufuncs.less_equal", "kind": "Gdef"}, "lexsort": {".class": "SymbolTableNode", "cross_ref": "jax._src.numpy.lax_numpy.lexsort", "kind": "Gdef"}, "linalg": {".class": "SymbolTableNode", "cross_ref": "jax.numpy.linalg", "kind": "Gdef"}, "linspace": {".class": "SymbolTableNode", "cross_ref": "jax._src.numpy.lax_numpy.linspace", "kind": "Gdef"}, "load": {".class": "SymbolTableNode", "cross_ref": "jax._src.numpy.lax_numpy.load", "kind": "Gdef"}, "log": {".class": "SymbolTableNode", "cross_ref": "jax._src.numpy.ufuncs.log", "kind": "Gdef"}, "log10": {".class": "SymbolTableNode", "cross_ref": "jax._src.numpy.ufuncs.log10", "kind": "Gdef"}, "log1p": {".class": "SymbolTableNode", "cross_ref": "jax._src.numpy.ufuncs.log1p", "kind": "Gdef"}, "log2": {".class": "SymbolTableNode", "cross_ref": "jax._src.numpy.ufuncs.log2", "kind": "Gdef"}, "logaddexp": {".class": "SymbolTableNode", "cross_ref": "jax._src.numpy.ufuncs.logaddexp", "kind": "Gdef"}, "logaddexp2": {".class": "SymbolTableNode", "cross_ref": "jax._src.numpy.ufuncs.logaddexp2", "kind": "Gdef"}, "logical_and": {".class": "SymbolTableNode", "cross_ref": "jax._src.numpy.ufuncs.logical_and", "kind": "Gdef"}, "logical_not": {".class": "SymbolTableNode", "cross_ref": "jax._src.numpy.ufuncs.logical_not", "kind": "Gdef"}, "logical_or": {".class": "SymbolTableNode", "cross_ref": "jax._src.numpy.ufuncs.logical_or", "kind": "Gdef"}, "logical_xor": {".class": "SymbolTableNode", "cross_ref": "jax._src.numpy.ufuncs.logical_xor", "kind": "Gdef"}, "logspace": {".class": "SymbolTableNode", "cross_ref": "jax._src.numpy.lax_numpy.logspace", "kind": "Gdef"}, "mask_indices": {".class": "SymbolTableNode", "cross_ref": "jax._src.numpy.lax_numpy.mask_indices", "kind": "Gdef"}, "matmul": {".class": "SymbolTableNode", "cross_ref": "jax._src.numpy.lax_numpy.matmul", "kind": "Gdef"}, "max": {".class": "SymbolTableNode", "cross_ref": "jax._src.numpy.reductions.max", "kind": "Gdef"}, "maximum": {".class": "SymbolTableNode", "cross_ref": "jax._src.numpy.ufuncs.maximum", "kind": "Gdef"}, "mean": {".class": "SymbolTableNode", "cross_ref": "jax._src.numpy.reductions.mean", "kind": "Gdef"}, "median": {".class": "SymbolTableNode", "cross_ref": "jax._src.numpy.lax_numpy.median", "kind": "Gdef"}, "meshgrid": {".class": "SymbolTableNode", "cross_ref": "jax._src.numpy.lax_numpy.meshgrid", "kind": "Gdef"}, "mgrid": {".class": "SymbolTableNode", "cross_ref": "jax._src.numpy.index_tricks.mgrid", "kind": "Gdef"}, "min": {".class": "SymbolTableNode", "cross_ref": "jax._src.numpy.reductions.min", "kind": "Gdef"}, "minimum": {".class": "SymbolTableNode", "cross_ref": "jax._src.numpy.ufuncs.minimum", "kind": "Gdef"}, "mod": {".class": "SymbolTableNode", "cross_ref": "jax._src.numpy.ufuncs.mod", "kind": "Gdef"}, "modf": {".class": "SymbolTableNode", "cross_ref": "jax._src.numpy.ufuncs.modf", "kind": "Gdef"}, "moveaxis": {".class": "SymbolTableNode", "cross_ref": "jax._src.numpy.lax_numpy.moveaxis", "kind": "Gdef"}, "msort": {".class": "SymbolTableNode", "cross_ref": "jax._src.numpy.lax_numpy.msort", "kind": "Gdef"}, "multiply": {".class": "SymbolTableNode", "cross_ref": "jax._src.numpy.ufuncs.multiply", "kind": "Gdef"}, "nan": {".class": "SymbolTableNode", "cross_ref": "jax._src.numpy.lax_numpy.nan", "kind": "Gdef"}, "nan_to_num": {".class": "SymbolTableNode", "cross_ref": "jax._src.numpy.lax_numpy.nan_to_num", "kind": "Gdef"}, "nanargmax": {".class": "SymbolTableNode", "cross_ref": "jax._src.numpy.lax_numpy.nanargmax", "kind": "Gdef"}, "nanargmin": {".class": "SymbolTableNode", "cross_ref": "jax._src.numpy.lax_numpy.nanargmin", "kind": "Gdef"}, "nancumprod": {".class": "SymbolTableNode", "cross_ref": "jax._src.numpy.reductions.nancumprod", "kind": "Gdef"}, "nancumsum": {".class": "SymbolTableNode", "cross_ref": "jax._src.numpy.reductions.nancumsum", "kind": "Gdef"}, "nanmax": {".class": "SymbolTableNode", "cross_ref": "jax._src.numpy.reductions.nanmax", "kind": "Gdef"}, "nanmean": {".class": "SymbolTableNode", "cross_ref": "jax._src.numpy.reductions.nanmean", "kind": "Gdef"}, "nanmedian": {".class": "SymbolTableNode", "cross_ref": "jax._src.numpy.lax_numpy.nanmedian", "kind": "Gdef"}, "nanmin": {".class": "SymbolTableNode", "cross_ref": "jax._src.numpy.reductions.nanmin", "kind": "Gdef"}, "nanpercentile": {".class": "SymbolTableNode", "cross_ref": "jax._src.numpy.lax_numpy.nanpercentile", "kind": "Gdef"}, "nanprod": {".class": "SymbolTableNode", "cross_ref": "jax._src.numpy.reductions.nanprod", "kind": "Gdef"}, "nanquantile": {".class": "SymbolTableNode", "cross_ref": "jax._src.numpy.lax_numpy.nanquantile", "kind": "Gdef"}, "nanstd": {".class": "SymbolTableNode", "cross_ref": "jax._src.numpy.reductions.nanstd", "kind": "Gdef"}, "nansum": {".class": "SymbolTableNode", "cross_ref": "jax._src.numpy.reductions.nansum", "kind": "Gdef"}, "nanvar": {".class": "SymbolTableNode", "cross_ref": "jax._src.numpy.reductions.nanvar", "kind": "Gdef"}, "ndarray": {".class": "SymbolTableNode", "cross_ref": "jax._src.numpy.ndarray.ndarray", "kind": "Gdef"}, "ndim": {".class": "SymbolTableNode", "cross_ref": "jax._src.numpy.lax_numpy.ndim", "kind": "Gdef"}, "negative": {".class": "SymbolTableNode", "cross_ref": "jax._src.numpy.ufuncs.negative", "kind": "Gdef"}, "newaxis": {".class": "SymbolTableNode", "cross_ref": "jax._src.numpy.lax_numpy.newaxis", "kind": "Gdef"}, "nextafter": {".class": "SymbolTableNode", "cross_ref": "jax._src.numpy.ufuncs.nextafter", "kind": "Gdef"}, "nonzero": {".class": "SymbolTableNode", "cross_ref": "jax._src.numpy.lax_numpy.nonzero", "kind": "Gdef"}, "not_equal": {".class": "SymbolTableNode", "cross_ref": "jax._src.numpy.ufuncs.not_equal", "kind": "Gdef"}, "number": {".class": "SymbolTableNode", "cross_ref": "jax._src.numpy.lax_numpy.number", "kind": "Gdef"}, "object_": {".class": "SymbolTableNode", "cross_ref": "jax._src.numpy.lax_numpy.object_", "kind": "Gdef"}, "ogrid": {".class": "SymbolTableNode", "cross_ref": "jax._src.numpy.index_tricks.ogrid", "kind": "Gdef"}, "ones": {".class": "SymbolTableNode", "cross_ref": "jax._src.numpy.lax_numpy.ones", "kind": "Gdef"}, "ones_like": {".class": "SymbolTableNode", "cross_ref": "jax._src.numpy.lax_numpy.ones_like", "kind": "Gdef"}, "outer": {".class": "SymbolTableNode", "cross_ref": "jax._src.numpy.lax_numpy.outer", "kind": "Gdef"}, "packbits": {".class": "SymbolTableNode", "cross_ref": "jax._src.numpy.lax_numpy.packbits", "kind": "Gdef"}, "pad": {".class": "SymbolTableNode", "cross_ref": "jax._src.numpy.lax_numpy.pad", "kind": "Gdef"}, "percentile": {".class": "SymbolTableNode", "cross_ref": "jax._src.numpy.lax_numpy.percentile", "kind": "Gdef"}, "pi": {".class": "SymbolTableNode", "cross_ref": "jax._src.numpy.lax_numpy.pi", "kind": "Gdef"}, "piecewise": {".class": "SymbolTableNode", "cross_ref": "jax._src.numpy.lax_numpy.piecewise", "kind": "Gdef"}, "poly": {".class": "SymbolTableNode", "cross_ref": "jax._src.numpy.polynomial.poly", "kind": "Gdef"}, "polyadd": {".class": "SymbolTableNode", "cross_ref": "jax._src.numpy.polynomial.polyadd", "kind": "Gdef"}, "polyder": {".class": "SymbolTableNode", "cross_ref": "jax._src.numpy.polynomial.polyder", "kind": "Gdef"}, "polydiv": {".class": "SymbolTableNode", "cross_ref": "jax._src.numpy.polynomial.polydiv", "kind": "Gdef"}, "polyfit": {".class": "SymbolTableNode", "cross_ref": "jax._src.numpy.polynomial.polyfit", "kind": "Gdef"}, "polyint": {".class": "SymbolTableNode", "cross_ref": "jax._src.numpy.polynomial.polyint", "kind": "Gdef"}, "polymul": {".class": "SymbolTableNode", "cross_ref": "jax._src.numpy.polynomial.polymul", "kind": "Gdef"}, "polysub": {".class": "SymbolTableNode", "cross_ref": "jax._src.numpy.polynomial.polysub", "kind": "Gdef"}, "polyval": {".class": "SymbolTableNode", "cross_ref": "jax._src.numpy.polynomial.polyval", "kind": "Gdef"}, "positive": {".class": "SymbolTableNode", "cross_ref": "jax._src.numpy.ufuncs.positive", "kind": "Gdef"}, "power": {".class": "SymbolTableNode", "cross_ref": "jax._src.numpy.ufuncs.power", "kind": "Gdef"}, "printoptions": {".class": "SymbolTableNode", "cross_ref": "jax._src.numpy.lax_numpy.printoptions", "kind": "Gdef"}, "prod": {".class": "SymbolTableNode", "cross_ref": "jax._src.numpy.reductions.prod", "kind": "Gdef"}, "product": {".class": "SymbolTableNode", "cross_ref": "jax._src.numpy.reductions.product", "kind": "Gdef"}, "promote_types": {".class": "SymbolTableNode", "cross_ref": "jax._src.numpy.lax_numpy.promote_types", "kind": "Gdef"}, "ptp": {".class": "SymbolTableNode", "cross_ref": "jax._src.numpy.reductions.ptp", "kind": "Gdef"}, "quantile": {".class": "SymbolTableNode", "cross_ref": "jax._src.numpy.lax_numpy.quantile", "kind": "Gdef"}, "r_": {".class": "SymbolTableNode", "cross_ref": "jax._src.numpy.index_tricks.r_", "kind": "Gdef"}, "rad2deg": {".class": "SymbolTableNode", "cross_ref": "jax._src.numpy.ufuncs.rad2deg", "kind": "Gdef"}, "radians": {".class": "SymbolTableNode", "cross_ref": "jax._src.numpy.ufuncs.radians", "kind": "Gdef"}, "ravel": {".class": "SymbolTableNode", "cross_ref": "jax._src.numpy.lax_numpy.ravel", "kind": "Gdef"}, "ravel_multi_index": {".class": "SymbolTableNode", "cross_ref": "jax._src.numpy.lax_numpy.ravel_multi_index", "kind": "Gdef"}, "real": {".class": "SymbolTableNode", "cross_ref": "jax._src.numpy.ufuncs.real", "kind": "Gdef"}, "reciprocal": {".class": "SymbolTableNode", "cross_ref": "jax._src.numpy.ufuncs.reciprocal", "kind": "Gdef"}, "remainder": {".class": "SymbolTableNode", "cross_ref": "jax._src.numpy.ufuncs.remainder", "kind": "Gdef"}, "repeat": {".class": "SymbolTableNode", "cross_ref": "jax._src.numpy.lax_numpy.repeat", "kind": "Gdef"}, "reshape": {".class": "SymbolTableNode", "cross_ref": "jax._src.numpy.lax_numpy.reshape", "kind": "Gdef"}, "resize": {".class": "SymbolTableNode", "cross_ref": "jax._src.numpy.lax_numpy.resize", "kind": "Gdef"}, "result_type": {".class": "SymbolTableNode", "cross_ref": "jax._src.numpy.lax_numpy.result_type", "kind": "Gdef"}, "right_shift": {".class": "SymbolTableNode", "cross_ref": "jax._src.numpy.ufuncs.right_shift", "kind": "Gdef"}, "rint": {".class": "SymbolTableNode", "cross_ref": "jax._src.numpy.ufuncs.rint", "kind": "Gdef"}, "roll": {".class": "SymbolTableNode", "cross_ref": "jax._src.numpy.lax_numpy.roll", "kind": "Gdef"}, "rollaxis": {".class": "SymbolTableNode", "cross_ref": "jax._src.numpy.lax_numpy.rollaxis", "kind": "Gdef"}, "roots": {".class": "SymbolTableNode", "cross_ref": "jax._src.numpy.polynomial.roots", "kind": "Gdef"}, "rot90": {".class": "SymbolTableNode", "cross_ref": "jax._src.numpy.lax_numpy.rot90", "kind": "Gdef"}, "round": {".class": "SymbolTableNode", "cross_ref": "jax._src.numpy.lax_numpy.round", "kind": "Gdef"}, "round_": {".class": "SymbolTableNode", "cross_ref": "jax._src.numpy.lax_numpy.round_", "kind": "Gdef"}, "row_stack": {".class": "SymbolTableNode", "cross_ref": "jax._src.numpy.lax_numpy.row_stack", "kind": "Gdef"}, "s_": {".class": "SymbolTableNode", "cross_ref": "jax._src.numpy.index_tricks.s_", "kind": "Gdef"}, "save": {".class": "SymbolTableNode", "cross_ref": "jax._src.numpy.lax_numpy.save", "kind": "Gdef"}, "savez": {".class": "SymbolTableNode", "cross_ref": "jax._src.numpy.lax_numpy.savez", "kind": "Gdef"}, "searchsorted": {".class": "SymbolTableNode", "cross_ref": "jax._src.numpy.lax_numpy.searchsorted", "kind": "Gdef"}, "select": {".class": "SymbolTableNode", "cross_ref": "jax._src.numpy.lax_numpy.select", "kind": "Gdef"}, "set_printoptions": {".class": "SymbolTableNode", "cross_ref": "jax._src.numpy.lax_numpy.set_printoptions", "kind": "Gdef"}, "setdiff1d": {".class": "SymbolTableNode", "cross_ref": "jax._src.numpy.setops.setdiff1d", "kind": "Gdef"}, "setxor1d": {".class": "SymbolTableNode", "cross_ref": "jax._src.numpy.setops.setxor1d", "kind": "Gdef"}, "shape": {".class": "SymbolTableNode", "cross_ref": "jax._src.numpy.lax_numpy.shape", "kind": "Gdef"}, "sign": {".class": "SymbolTableNode", "cross_ref": "jax._src.numpy.ufuncs.sign", "kind": "Gdef"}, "signbit": {".class": "SymbolTableNode", "cross_ref": "jax._src.numpy.ufuncs.signbit", "kind": "Gdef"}, "signedinteger": {".class": "SymbolTableNode", "cross_ref": "jax._src.numpy.lax_numpy.signedinteger", "kind": "Gdef"}, "sin": {".class": "SymbolTableNode", "cross_ref": "jax._src.numpy.ufuncs.sin", "kind": "Gdef"}, "sinc": {".class": "SymbolTableNode", "cross_ref": "jax._src.numpy.ufuncs.sinc", "kind": "Gdef"}, "single": {".class": "SymbolTableNode", "cross_ref": "jax._src.numpy.lax_numpy.single", "kind": "Gdef"}, "sinh": {".class": "SymbolTableNode", "cross_ref": "jax._src.numpy.ufuncs.sinh", "kind": "Gdef"}, "size": {".class": "SymbolTableNode", "cross_ref": "jax._src.numpy.lax_numpy.size", "kind": "Gdef"}, "sometrue": {".class": "SymbolTableNode", "cross_ref": "jax._src.numpy.reductions.sometrue", "kind": "Gdef"}, "sort": {".class": "SymbolTableNode", "cross_ref": "jax._src.numpy.lax_numpy.sort", "kind": "Gdef"}, "sort_complex": {".class": "SymbolTableNode", "cross_ref": "jax._src.numpy.lax_numpy.sort_complex", "kind": "Gdef"}, "split": {".class": "SymbolTableNode", "cross_ref": "jax._src.numpy.lax_numpy.split", "kind": "Gdef"}, "sqrt": {".class": "SymbolTableNode", "cross_ref": "jax._src.numpy.ufuncs.sqrt", "kind": "Gdef"}, "square": {".class": "SymbolTableNode", "cross_ref": "jax._src.numpy.ufuncs.square", "kind": "Gdef"}, "squeeze": {".class": "SymbolTableNode", "cross_ref": "jax._src.numpy.lax_numpy.squeeze", "kind": "Gdef"}, "stack": {".class": "SymbolTableNode", "cross_ref": "jax._src.numpy.lax_numpy.stack", "kind": "Gdef"}, "std": {".class": "SymbolTableNode", "cross_ref": "jax._src.numpy.reductions.std", "kind": "Gdef"}, "subtract": {".class": "SymbolTableNode", "cross_ref": "jax._src.numpy.ufuncs.subtract", "kind": "Gdef"}, "sum": {".class": "SymbolTableNode", "cross_ref": "jax._src.numpy.reductions.sum", "kind": "Gdef"}, "swapaxes": {".class": "SymbolTableNode", "cross_ref": "jax._src.numpy.lax_numpy.swapaxes", "kind": "Gdef"}, "take": {".class": "SymbolTableNode", "cross_ref": "jax._src.numpy.lax_numpy.take", "kind": "Gdef"}, "take_along_axis": {".class": "SymbolTableNode", "cross_ref": "jax._src.numpy.lax_numpy.take_along_axis", "kind": "Gdef"}, "tan": {".class": "SymbolTableNode", "cross_ref": "jax._src.numpy.ufuncs.tan", "kind": "Gdef"}, "tanh": {".class": "SymbolTableNode", "cross_ref": "jax._src.numpy.ufuncs.tanh", "kind": "Gdef"}, "tensordot": {".class": "SymbolTableNode", "cross_ref": "jax._src.numpy.lax_numpy.tensordot", "kind": "Gdef"}, "tile": {".class": "SymbolTableNode", "cross_ref": "jax._src.numpy.lax_numpy.tile", "kind": "Gdef"}, "trace": {".class": "SymbolTableNode", "cross_ref": "jax._src.numpy.lax_numpy.trace", "kind": "Gdef"}, "transpose": {".class": "SymbolTableNode", "cross_ref": "jax._src.numpy.lax_numpy.transpose", "kind": "Gdef"}, "trapz": {".class": "SymbolTableNode", "cross_ref": "jax._src.numpy.lax_numpy.trapz", "kind": "Gdef"}, "tri": {".class": "SymbolTableNode", "cross_ref": "jax._src.numpy.lax_numpy.tri", "kind": "Gdef"}, "tril": {".class": "SymbolTableNode", "cross_ref": "jax._src.numpy.lax_numpy.tril", "kind": "Gdef"}, "tril_indices": {".class": "SymbolTableNode", "cross_ref": "jax._src.numpy.lax_numpy.tril_indices", "kind": "Gdef"}, "tril_indices_from": {".class": "SymbolTableNode", "cross_ref": "jax._src.numpy.lax_numpy.tril_indices_from", "kind": "Gdef"}, "trim_zeros": {".class": "SymbolTableNode", "cross_ref": "jax._src.numpy.lax_numpy.trim_zeros", "kind": "Gdef"}, "triu": {".class": "SymbolTableNode", "cross_ref": "jax._src.numpy.lax_numpy.triu", "kind": "Gdef"}, "triu_indices": {".class": "SymbolTableNode", "cross_ref": "jax._src.numpy.lax_numpy.triu_indices", "kind": "Gdef"}, "triu_indices_from": {".class": "SymbolTableNode", "cross_ref": "jax._src.numpy.lax_numpy.triu_indices_from", "kind": "Gdef"}, "true_divide": {".class": "SymbolTableNode", "cross_ref": "jax._src.numpy.ufuncs.true_divide", "kind": "Gdef"}, "trunc": {".class": "SymbolTableNode", "cross_ref": "jax._src.numpy.lax_numpy.trunc", "kind": "Gdef"}, "uint": {".class": "SymbolTableNode", "cross_ref": "jax._src.numpy.lax_numpy.uint", "kind": "Gdef"}, "uint16": {".class": "SymbolTableNode", "cross_ref": "jax._src.numpy.lax_numpy.uint16", "kind": "Gdef"}, "uint32": {".class": "SymbolTableNode", "cross_ref": "jax._src.numpy.lax_numpy.uint32", "kind": "Gdef"}, "uint64": {".class": "SymbolTableNode", "cross_ref": "jax._src.numpy.lax_numpy.uint64", "kind": "Gdef"}, "uint8": {".class": "SymbolTableNode", "cross_ref": "jax._src.numpy.lax_numpy.uint8", "kind": "Gdef"}, "union1d": {".class": "SymbolTableNode", "cross_ref": "jax._src.numpy.setops.union1d", "kind": "Gdef"}, "unique": {".class": "SymbolTableNode", "cross_ref": "jax._src.numpy.setops.unique", "kind": "Gdef"}, "unpackbits": {".class": "SymbolTableNode", "cross_ref": "jax._src.numpy.lax_numpy.unpackbits", "kind": "Gdef"}, "unravel_index": {".class": "SymbolTableNode", "cross_ref": "jax._src.numpy.lax_numpy.unravel_index", "kind": "Gdef"}, "unsignedinteger": {".class": "SymbolTableNode", "cross_ref": "jax._src.numpy.lax_numpy.unsignedinteger", "kind": "Gdef"}, "unwrap": {".class": "SymbolTableNode", "cross_ref": "jax._src.numpy.lax_numpy.unwrap", "kind": "Gdef"}, "vander": {".class": "SymbolTableNode", "cross_ref": "jax._src.numpy.lax_numpy.vander", "kind": "Gdef"}, "var": {".class": "SymbolTableNode", "cross_ref": "jax._src.numpy.reductions.var", "kind": "Gdef"}, "vdot": {".class": "SymbolTableNode", "cross_ref": "jax._src.numpy.lax_numpy.vdot", "kind": "Gdef"}, "vectorize": {".class": "SymbolTableNode", "cross_ref": "jax._src.numpy.vectorize.vectorize", "kind": "Gdef"}, "vsplit": {".class": "SymbolTableNode", "cross_ref": "jax._src.numpy.lax_numpy.vsplit", "kind": "Gdef"}, "vstack": {".class": "SymbolTableNode", "cross_ref": "jax._src.numpy.lax_numpy.vstack", "kind": "Gdef"}, "where": {".class": "SymbolTableNode", "cross_ref": "jax._src.numpy.lax_numpy.where", "kind": "Gdef"}, "zeros": {".class": "SymbolTableNode", "cross_ref": "jax._src.numpy.lax_numpy.zeros", "kind": "Gdef"}, "zeros_like": {".class": "SymbolTableNode", "cross_ref": "jax._src.numpy.lax_numpy.zeros_like", "kind": "Gdef"}}, "path": "/home/paperspace/.pyenv/versions/3.10.4/lib/python3.10/site-packages/jax/numpy/__init__.py"}